pyaklass/__init__.py
pyaklass/account.py
pyaklass/const.py
pyaklass/exc.py
pyaklass/manager.py
pyaklass/parse/__init__.py
pyaklass/parse/completed.py
pyaklass/parse/func.py
pyaklass/parse/new.py
pyaklass/parse/results.py
pyaklass/testworks.py
pyaklass-1.1.0.dist-info/LICENSE
pyaklass-1.1.0.dist-info/METADATA
pyaklass-1.1.0.dist-info/WHEEL
pyaklass-1.1.0.dist-info/RECORD
