Metadata-Version: 2.1
Name: pyaklass
Version: 1.1.0
Summary: Module for communicating with a russian education website - YaKlass.
Home-page: https://codeberg.org/teapon/pyaklass
License: MIT
Keywords: library,module,client,python3,pyaklass,russian,russia,education,parse,parsing
Author: Teapon
Author-email: teapon@keemail.me
Requires-Python: >=3.10,<4.0
Classifier: Development Status :: 5 - Production/Stable
Classifier: Framework :: AsyncIO
Classifier: Intended Audience :: Developers
Classifier: License :: OSI Approved
Classifier: License :: OSI Approved :: MIT License
Classifier: Natural Language :: Russian
Classifier: Programming Language :: Python
Classifier: Programming Language :: Python :: 3
Classifier: Programming Language :: Python :: 3.10
Classifier: Programming Language :: Python :: 3.11
Classifier: Programming Language :: Python :: 3 :: Only
Classifier: Topic :: Education
Classifier: Topic :: Internet
Classifier: Topic :: Internet :: WWW/HTTP
Classifier: Topic :: Software Development
Classifier: Topic :: Software Development :: Libraries
Classifier: Topic :: Software Development :: Libraries :: Python Modules
Requires-Dist: httpx (>=0.24.0,<0.25.0)
Requires-Dist: selectolax (>=0.3.13,<0.4.0)
Project-URL: Repository, https://codeberg.org/teapon/pyaklass
